jaydee/__init__.py
jaydee/crawlers/__init__.py
jaydee/crawlers/base.py
jaydee/crawlers/git.py
jaydee/crawlers/link.py
jaydee/options/__init__.py
jaydee/options/crawlers.py
jaydee/options/multithread.py
jaydee/options/scraper.py
jaydee/options/waitfor.py
jaydee/options/webscraper.py
jaydee/scraper.py
jaydee/utils.py
jaydee/webscraper.py
jaydee-0.1.12.dist-info/LICENSE
jaydee-0.1.12.dist-info/METADATA
jaydee-0.1.12.dist-info/WHEEL
jaydee-0.1.12.dist-info/entry_points.txt
jaydee-0.1.12.dist-info/RECORD
