Metadata-Version: 2.1
Name: jaydee
Version: 0.1.12
Summary: Crawl and scrape websites with a given .json schema.
License: MIT
Author: Anttoni Koivu
Requires-Python: >=3.11,<4.0
Classifier: License :: OSI Approved :: MIT License
Classifier: Programming Language :: Python :: 3
Classifier: Programming Language :: Python :: 3.11
Classifier: Programming Language :: Python :: 3.12
Classifier: Programming Language :: Python :: 3.13
Requires-Dist: beautifulsoup4 (==4.12.3)
Requires-Dist: html5lib (>=1.1,<2.0)
Requires-Dist: playwright (>=1.49.0,<2.0.0)
